{"learner":{"attributes":{"best_iteration":"99","best_ntree_limit":"100","scikit_learn":"{\"n_estimators\": 100, \"objective\": \"reg:squarederror\", \"max_depth\": null, \"learning_rate\": null, \"verbosity\": null, \"booster\": null, \"tree_method\": null, \"gamma\": null, \"min_child_weight\": null, \"max_delta_step\": null, \"subsample\": null, \"colsample_bytree\": null, \"colsample_bylevel\": null, \"colsample_bynode\": null, \"reg_alpha\": null, \"reg_lambda\": null, \"scale_pos_weight\": null, \"base_score\": null, \"missing\": NaN, \"num_parallel_tree\": null, \"random_state\": null, \"n_jobs\": null, \"monotone_constraints\": null, \"interaction_constraints\": null, \"importance_type\": null, \"gpu_id\": null, \"validate_parameters\": null, \"predictor\": null, \"enable_categorical\": false, \"_estimator_type\": \"regressor\"}"},"feature_names":[],"feature_types":[],"gradient_booster":{"model":{"gbtree_model_param":{"num_trees":"100","size_leaf_vector":"0"},"tree_info":[0,0,0,0,0,0,0,0,0,0,0,0,0,0,0,0,0,0,0,0,0,0,0,0,0,0,0,0,0,0,0,0,0,0,0,0,0,0,0,0,0,0,0,0,0,0,0,0,0,0,0,0,0,0,0,0,0,0,0,0,0,0,0,0,0,0,0,0,0,0,0,0,0,0,0,0,0,0,0,0,0,0,0,0,0,0,0,0,0,0,0,0,0,0,0,0,0,0,0,0],"trees":[{"base_weights":[3.0652054E2],"categories":[],"categories_nodes":[],"categories_segments":[],"categories_sizes":[],"default_left":[false],"id":0,"left_children":[-1],"loss_changes":[0E0],"parents":[2147483647],"right_children":[-1],"split_conditions":[9.195616E1],"split_indices":[0],"split_type":[0],"sum_hessian":[3.7E1],"tree_param":{"num_deleted":"0","num_feature":"4","num_nodes":"1","size_leaf_vector":"0"}},{"base_weights":[2.1698427E2],"categories":[],"categories_nodes":[],"categories_segments":[],"categories_sizes":[],"default_left":[false],"id":1,"left_children":[-1],"loss_changes":[0E0],"parents":[2147483647],"right_children":[-1],"split_conditions":[6.509528E1],"split_indices":[0],"split_type":[0],"sum_hessian":[3.7E1],"tree_param":{"num_deleted":"0","num_feature":"4","num_nodes":"1","size_leaf_vector":"0"}},{"base_weights":[1.53602E2,1.1210865E2,1.7069421E2],"categories":[],"categories_nodes":[],"categories_segments":[],"categories_sizes":[],"default_left":[true,false,false],"id":2,"left_children":[1,-1,-1],"loss_changes":[7.81375E3,0E0,0E0],"parents":[2147483647,0,0],"right_children":[2,-1,-1],"split_conditions":[1.25E2,3.3632595E1,5.1208267E1],"split_indices":[1,0,0],"split_type":[0,0,0],"sum_hessian":[3.7E1,1.3E1,2.4E1],"tree_param":{"num_deleted":"0","num_feature":"4","num_nodes":"3","size_leaf_vector":"0"}},{"base_weights":[1.0975406E2,8.087838E1,1.2153427E2],"categories":[],"categories_nodes":[],"categories_segments":[],"categories_sizes":[],"default_left":[true,false,false],"id":3,"left_children":[1,-1,-1],"loss_changes":[3.0966562E3,0E0,0E0],"parents":[2147483647,0,0],"right_children":[2,-1,-1],"split_conditions":[1.25E2,2.4263515E1,3.646028E1],"split_indices":[1,0,0],"split_type":[0,0,0],"sum_hessian":[3.7E1,1.3E1,2.4E1],"tree_param":{"num_deleted":"0","num_feature":"4","num_nodes":"3","size_leaf_vector":"0"}},{"base_weights":[7.8425835E1,5.834797E1,8.65324E1,1.0081923E2,6.558923E1],"categories":[],"categories_nodes":[],"categories_segments":[],"categories_sizes":[],"default_left":[true,false,true,false,false],"id":4,"left_children":[1,-1,3,-1,-1],"loss_changes":[1.1359844E3,0E0,8.67625E2,0E0,0E0],"parents":[2147483647,0,0,2,2],"right_children":[2,-1,4,-1,-1],"split_conditions":[1.25E2,1.750439E1,1.75E2,3.024577E1,1.9676771E1],"split_indices":[1,0,1,0,0],"split_type":[0,0,0,0,0],"sum_hessian":[3.7E1,1.3E1,2.4E1,1.2E1,1.2E1],"tree_param":{"num_deleted":"0","num_feature":"4","num_nodes":"5","size_leaf_vector":"0"}},{"base_weights":[5.667248E1,4.2093887E1,6.2569595E1,4.737523E1,2.3112432E1,7.290007E1,4.7426075E1],"categories":[],"categories_nodes":[],"categories_segments":[],"categories_sizes":[],"default_left":[true,true,true,false,false,false,false],"id":5,"left_children":[1,3,5,-1,-1,-1,-1],"loss_changes":[6.33125E2,3.0850586E2,4.53625E2,0E0,0E0,0E0,0E0],"parents":[2147483647,0,0,1,1,2,2],"right_children":[2,4,6,-1,-1,-1,-1],"split_conditions":[1.25E2,1.1E-1,1.75E2,1.4212569E1,6.93373E0,2.1870022E1,1.4227823E1],"split_indices":[1,3,1,0,0,0,0],"split_type":[0,0,0,0,0,0,0],"sum_hessian":[3.7E1,1.3E1,2.4E1,9E0,4E0,1.2E1,1.2E1],"tree_param":{"num_deleted":"0","num_feature":"4","num_nodes":"7","size_leaf_vector":"0"}},{"base_weights":[4.1177162E1,5.149225E1,3.4435883E1,2.2108454E1,3.966167E1,4.7914936E1,2.909289E1],"categories":[],"categories_nodes":[],"categories_segments":[],"categories_sizes":[],"default_left":[true,false,true,false,true,false,false],"id":6,"left_children":[1,-1,3,-1,5,-1,-1],"loss_changes":[8.6921875E2,0E0,7.980742E2,0E0,8.8875E1,0E0,0E0],"parents":[2147483647,0,0,2,2,4,4],"right_children":[2,-1,4,-1,6,-1,-1],"split_conditions":[9E-2,1.5447675E1,1.25E2,6.6325364E0,1.75E2,1.4374481E1,8.727867E0],"split_indices":[3,0,1,0,1,0,0],"split_type":[0,0,0,0,0,0,0],"sum_hessian":[3.7E1,1.2E1,2.5E1,9E0,1.6E1,7E0,9E0],"tree_param":{"num_deleted":"0","num_feature":"4","num_nodes":"7","size_leaf_vector":"0"}},{"base_weights":[3.0013027E1,3.7232864E1,2.5248762E1,1.613917E1,2.9122126E1,3.5337265E1,2.1237803E1],"categories":[],"categories_nodes":[],"categories_segments":[],"categories_sizes":[],"default_left":[true,false,true,false,true,false,false],"id":7,"left_children":[1,-1,3,-1,5,-1,-1],"loss_changes":[3.670078E2,0E0,4.4739844E2,0E0,8.255078E1,0E0,0E0],"parents":[2147483647,0,0,2,2,4,4],"right_children":[2,-1,4,-1,6,-1,-1],"split_conditions":[9E-2,1.116986E1,1.25E2,4.841751E0,1.75E2,1.060118E1,6.371341E0],"split_indices":[3,0,1,0,1,0,0],"split_type":[0,0,0,0,0,0,0],"sum_hessian":[3.7E1,1.2E1,2.5E1,9E0,1.6E1,7E0,9E0],"tree_param":{"num_deleted":"0","num_feature":"4","num_nodes":"7","size_leaf_vector":"0"}},{"base_weights":[2.1877125E1,2.4300745E1,1.4600888E1,2.6590027E1,1.6767733E1,8.386017E0,1.6660072E1,2.939853E1,1.5605184E1],"categories":[],"categories_nodes":[],"categories_segments":[],"categories_sizes":[],"default_left":[true,true,true,true,false,false,false,false,false],"id":8,"left_children":[1,3,5,7,-1,-1,-1,-1,-1],"loss_changes":[3.1531055E2,1.9765625E1,1.3859131E1,1.2739844E2,0E0,0E0,0E0,0E0,0E0],"parents":[2147483647,0,0,1,1,2,2,3,3],"right_children":[2,4,6,8,-1,-1,-1,-1,-1],"split_conditions":[1.1E-1,6.5E3,1.25E2,1.75E2,5.03032E0,2.5158052E0,4.998022E0,8.819559E0,4.6815553E0],"split_indices":[3,0,1,1,0,0,0,0,0],"split_type":[0,0,0,0,0,0,0,0,0],"sum_hessian":[3.7E1,2.6E1,1.1E1,1.8E1,8E0,4E0,7E0,1.3E1,5E0],"tree_param":{"num_deleted":"0","num_feature":"4","num_nodes":"9","size_leaf_vector":"0"}},{"base_weights":[1.5999391E1,1.0959609E1,1.8181694E1,1.4166699E1,8.260103E0,2.1767185E1,1.3197608E1],"categories":[],"categories_nodes":[],"categories_segments":[],"categories_sizes":[],"default_left":[true,true,true,false,false,false,false],"id":9,"left_children":[1,3,5,-1,-1,-1,-1],"loss_changes":[2.186709E2,4.187378E0,1.5948535E2,0E0,0E0,0E0,0E0],"parents":[2147483647,0,0,1,1,2,2],"right_children":[2,4,6,-1,-1,-1,-1],"split_conditions":[1.25E2,3.5E3,1.75E2,4.25001E0,2.4780312E0,6.5301557E0,3.9592826E0],"split_indices":[1,0,1,0,0,0,0],"split_type":[0,0,0,0,0,0,0],"sum_hessian":[3.7E1,1.3E1,2.4E1,4E0,9E0,1.2E1,1.2E1],"tree_param":{"num_deleted":"0","num_feature":"4","num_nodes":"7","size_leaf_vector":"0"}},{"base_weights":[1.1652666E1,1.3258508E1,7.068466E0,9.217753E0,1.47667885E1,8.404485E0,1.656733E1],"categories":[],"categories_nodes":[],"categories_segments":[],"categories_sizes":[],"default_left":[true,true,false,false,true,false,false],"id":10,"left_children":[1,3,-1,-1,5,-1,-1],"loss_changes":[1.8601953E2,2.84375E1,0E0,0E0,6.696094E1,0E0,0E0],"parents":[2147483647,0,0,1,1,4,4],"right_children":[2,4,-1,-1,6,-1,-1],"split_conditions":[1.1E-1,1.25E2,2.12054E0,2.765326E0,6E2,2.5213456E0,4.970199E0],"split_indices":[3,1,0,0,2,0,0],"split_type":[0,0,0,0,0,0,0],"sum_hessian":[3.7E1,2.6E1,1.1E1,9E0,1.7E1,5E0,1.2E1],"tree_param":{"num_deleted":"0","num_feature":"4","num_nodes":"7","size_leaf_vector":"0"}},{"base_weights":[8.4825945E0,9.660851E0,5.124634E0,1.0693748E1,6.4068623E0,3.3962266E0,7.7323914E0,1.1811498E1,6.3033752E0,4.0862403E0,8.286079E0],"categories":[],"categories_nodes":[],"categories_segments":[],"categories_sizes":[],"default_left":[true,true,true,true,true,false,false,false,false,false,false],"id":11,"left_children":[1,3,5,7,9,-1,-1,-1,-1,-1,-1],"loss_changes":[1.0084009E2,2.223462E1,2.7826233E1,1.8786865E1,5.3896484E0,0E0,0E0,0E0,0E0,0E0,0E0],"parents":[2147483647,0,0,1,1,2,2,3,3,4,4],"right_children":[2,4,6,8,10,-1,-1,-1,-1,-1,-1],"split_conditions":[1.1E-1,6.5E3,6.5E3,1.75E2,1.5E2,1.0188681E0,2.3197174E0,3.5434494E0,1.8910127E0,1.2258722E0,2.4858239E0],"split_indices":[3,0,0,1,1,0,0,0,0,0,0],"split_type":[0,0,0,0,0,0,0,0,0,0,0],"sum_hessian":[3.7E1,2.6E1,1.1E1,1.8E1,8E0,8E0,3E0,1.3E1,5E0,5E0,3E0],"tree_param":{"num_deleted":"0","num_feature":"4","num_nodes":"11","size_leaf_vector":"0"}},{"base_weights":[6.2663636E0,4.027404E0,7.2695265E0,5.719678E0,2.7785263E0,8.820622E0,5.159236E0,2.6036072E0,6.005781E0],"categories":[],"categories_nodes":[],"categories_segments":[],"categories_sizes":[],"default_left":[true,true,true,false,false,false,true,false,false],"id":12,"left_children":[1,3,5,-1,-1,-1,7,-1,-1],"loss_changes":[5.6072266E1,1.3695923E1,3.6323853E1,0E0,0E0,0E0,1.2488251E1,0E0,0E0],"parents":[2147483647,0,0,1,1,2,2,6,6],"right_children":[2,4,6,-1,-1,-1,8,-1,-1],"split_conditions":[1.25E2,3.5E3,1.75E2,1.7159034E0,8.335579E-1,2.6461868E0,3.5E3,7.810822E-1,1.8017344E0],"split_indices":[1,0,1,0,0,0,0,0,0],"split_type":[0,0,0,0,0,0,0,0,0],"sum_hessian":[3.7E1,1.3E1,2.4E1,4E0,9E0,1.2E1,1.2E1,4E0,8E0],"tree_param":{"num_deleted":"0","num_feature":"4","num_nodes":"9","size_leaf_vector":"0"}},{"base_weights":[4.591152E0,5.276864E0,2.6657054E0,3.5955093E0,5.917791E0,1.7729492E0,4.0079803E0,3.2260845E0,6.704902E0],"categories":[],"categories_nodes":[],"categories_segments":[],"categories_sizes":[],"default_left":[true,true,true,false,true,false,false,false,false],"id":13,"left_children":[1,3,5,-1,7,-1,-1,-1,-1],"loss_changes":[3.610486E1,7.8183594E0,7.273941E0,0E0,1.6505554E1,0E0,0E0,0E0,0E0],"parents":[2147483647,0,0,1,1,2,2,4,4],"right_children":[2,4,6,-1,8,-1,-1,-1,-1],"split_conditions":[1.1E-1,1.25E2,6.5E3,1.0786529E0,6E2,5.318848E-1,1.2023941E0,9.6782535E-1,2.0114708E0],"split_indices":[3,1,0,0,2,0,0,0,0],"split_type":[0,0,0,0,0,0,0,0,0],"sum_hessian":[3.7E1,2.6E1,1.1E1,9E0,1.7E1,8E0,3E0,5E0,1.2E1],"tree_param":{"num_deleted":"0","num_feature":"4","num_nodes":"9","size_leaf_vector":"0"}},{"base_weights":[3.3662322E0,3.8440988E0,2.0105133E0,2.6247299E0,4.307965E0,7.8706664E-1,2.5238533E0,3.484033E0,1.4711889E0,2.4195557E0,4.8481565E0],"categories":[],"categories_nodes":[],"categories_segments":[],"categories_sizes":[],"default_left":[true,true,true,true,true,false,false,false,false,false,false],"id":14,"left_children":[1,3,5,7,9,-1,-1,-1,-1,-1,-1],"loss_changes":[1.6889801E1,3.9645996E0,5.550087E0,4.786743E0,6.6314697E0,0E0,0E0,0E0,0E0,0E0,0E0],"parents":[2147483647,0,0,1,1,2,2,3,3,4,4],"right_children":[2,4,6,8,10,-1,-1,-1,-1,-1,-1],"split_conditions":[1.1E-1,1.25E2,1.25E2,5E3,6E2,2.3612E-1,7.57156E-1,1.04521E0,4.413567E-1,7.2586673E-1,1.454447E0],"split_indices":[3,1,1,0,2,0,0,0,0,0,0],"split_type":[0,0,0,0,0,0,0,0,0,0,0],"sum_hessian":[3.7E1,2.6E1,1.1E1,9E0,1.7E1,4E0,7E0,4E0,5E0,5E0,1.2E1],"tree_param":{"num_deleted":"0","num_feature":"4","num_nodes":"11","size_leaf_vector":"0"}},{"base_weights":[2.4790084E0,2.826689E0,1.4901428E0,3.1482222E0,1.8338199E0,8.587104E-1,2.53833E0,3.494871E0,1.8146719E0,1.1034012E0,2.470993E0],"categories":[],"categories_nodes":[],"categories_segments":[],"categories_sizes":[],"default_left":[true,true,true,true,true,false,false,false,false,false,false],"id":15,"left_children":[1,3,5,7,9,-1,-1,-1,-1,-1,-1],"loss_changes":[8.852585E0,2.8462067E0,5.762621E0,2.441162E0,1.4621315E0,0E0,0E0,0E0,0E0,0E0,0E0],"parents":[2147483647,0,0,1,1,2,2,3,3,4,4],"right_children":[2,4,6,8,10,-1,-1,-1,-1,-1,-1],"split_conditions":[1.1E-1,6.5E3,6.5E3,1.75E2,1.5E2,2.5761312E-1,7.6149905E-1,1.0484613E0,5.444016E-1,3.3102036E-1,7.4129796E-1],"split_indices":[3,0,0,1,1,0,0,0,0,0,0],"split_type":[0,0,0,0,0,0,0,0,0,0,0],"sum_hessian":[3.7E1,2.6E1,1.1E1,1.8E1,8E0,8E0,3E0,1.3E1,5E0,5E0,3E0],"tree_param":{"num_deleted":"0","num_feature":"4","num_nodes":"11","size_leaf_vector":"0"}},{"base_weights":[1.8322622E0,1.140807E0,2.1461866E0,1.8091065E0,6.925766E-1,2.6247277E0,1.502554E0,3.9209595E-1,8.275477E-1,7.4142456E-1,1.7584534E0],"categories":[],"categories_nodes":[],"categories_segments":[],"categories_sizes":[],"default_left":[true,true,true,false,true,false,true,false,false,false,false],"id":16,"left_children":[1,3,5,-1,7,-1,9,-1,-1,-1,-1],"loss_changes":[5.800064E0,2.9407845E0,3.7563171E0,0E0,8.108425E-2,0E0,1.2282829E0,0E0,0E0,0E0,0E0],"parents":[2147483647,0,0,1,1,2,2,4,4,6,6],"right_children":[2,4,6,-1,8,-1,10,-1,-1,-1,-1],"split_conditions":[1.25E2,3.5E3,1.75E2,5.4273194E-1,6.5E3,7.8741837E-1,3.5E3,1.1762879E-1,2.4826433E-1,2.2242738E-1,5.2753603E-1],"split_indices":[1,0,1,0,0,0,0,0,0,0,0],"split_type":[0,0,0,0,0,0,0,0,0,0,0],"sum_hessian":[3.7E1,1.3E1,2.4E1,4E0,9E0,1.2E1,1.2E1,4E0,5E0,4E0,8E0],"tree_param":{"num_deleted":"0","num_feature":"4","num_nodes":"11","size_leaf_vector":"0"}},{"base_weights":[1.3469564E0,8.634742E-1,1.5638281E0,1.3749268E0,5.2140045E-1,1.8978835E0,1.1094782E0,2.9800415E-1,6.2066394E-1,5.634705E-1,1.2895406E0],"categories":[],"categories_nodes":[],"categories_segments":[],"categories_sizes":[],"default_left":[true,true,true,false,true,false,true,false,false,false,false],"id":17,"left_children":[1,3,5,-1,7,-1,9,-1,-1,-1,-1],"loss_changes":[2.6341095E0,1.7324753E0,1.6887894E0,0E0,3.679061E-2,0E0,5.5148315E-1,0E0,0E0,0E0,0E0],"parents":[2147483647,0,0,1,1,2,2,4,4,6,6],"right_children":[2,4,6,-1,8,-1,10,-1,-1,-1,-1],"split_conditions":[1.25E2,3.5E3,1.75E2,4.1247806E-1,6.5E3,5.693651E-1,3.5E3,8.9401245E-2,1.8619919E-1,1.6904116E-1,3.8686222E-1],"split_indices":[1,0,1,0,0,0,0,0,0,0,0],"split_type":[0,0,0,0,0,0,0,0,0,0,0],"sum_hessian":[3.7E1,1.3E1,2.4E1,4E0,9E0,1.2E1,1.2E1,4E0,5E0,4E0,8E0],"tree_param":{"num_deleted":"0","num_feature":"4","num_nodes":"11","size_leaf_vector":"0"}},{"base_weights":[9.905906E-1,1.1322333E0,5.893453E-1,8.0177766E-1,1.2529178E0,3.637424E-1,9.496155E-1,1.0449463E0,4.655075E-1,5.990041E-1,1.4583459E0],"categories":[],"categories_nodes":[],"categories_segments":[],"categories_sizes":[],"default_left":[true,true,true,true,true,false,false,false,false,false,false],"id":18,"left_children":[1,3,5,7,9,-1,-1,-1,-1,-1,-1],"loss_changes":[1.4923935E0,7.222366E-2,6.2992096E-1,3.3127308E-1,1.544426E0,0E0,0E0,0E0,0E0,0E0,0E0],"parents":[2147483647,0,0,1,1,2,2,3,3,4,4],"right_children":[2,4,6,8,10,-1,-1,-1,-1,-1,-1],"split_conditions":[1.1E-1,1.25E2,6.5E3,5E3,6E2,1.0912273E-1,2.8488466E-1,3.134839E-1,1.3965225E-1,1.7970124E-1,4.3750378E-1],"split_indices":[3,1,0,0,2,0,0,0,0,0,0],"split_type":[0,0,0,0,0,0,0,0,0,0,0],"sum_hessian":[3.7E1,2.6E1,1.1E1,9E0,1.7E1,8E0,3E0,4E0,5E0,5E0,1.2E1],"tree_param":{"num_deleted":"0","num_feature":"4","num_nodes":"11","size_leaf_vector":"0"}},{"base_weights":[7.3195165E-1,8.3221155E-1,4.45371E-1,1.0347086E0,6.9249123E-1,2.667372E-1,7.359543E-1,9.296604E-1,4.3549E-1,3.4093627E-1,1.3919067E-1],"categories":[],"categories_nodes":[],"categories_segments":[],"categories_sizes":[],"default_left":[true,true,true,false,true,true,false,false,false,false,false],"id":19,"left_children":[1,3,5,-1,7,9,-1,-1,-1,-1,-1],"loss_changes":[7.211933E-1,4.7384262E-2,4.2658973E-1,0E0,7.532444E-1,3.771937E-2,0E0,0E0,0E0,0E0,0E0],"parents":[2147483647,0,0,1,1,2,2,4,4,5,5],"right_children":[2,4,6,-1,8,10,-1,-1,-1,-1,-1],"split_conditions":[1.1E-1,3.5E3,6.5E3,3.104126E-1,9E-2,3.5E3,2.2078629E-1,2.7889812E-1,1.30647E-1,1.02280885E-1,4.1757204E-2],"split_indices":[3,0,0,0,3,0,0,0,0,0,0],"split_type":[0,0,0,0,0,0,0,0,0,0,0],"sum_hessian":[3.7E1,2.6E1,1.1E1,8E0,1.8E1,8E0,3E0,8E0,1E1,4E0,4E0],"tree_param":{"num_deleted":"0","num_feature":"4","num_nodes":"11","size_leaf_vector":"0"}},{"base_weights":[5.4090923E-1,3.3569008E-1,6.3419557E-1,5.458252E-1,1.9705352E-1,7.499507E-1,4.6965614E-1,1.0579224E-1,2.4026234E-1,3.33786E-1,6.919174E-1],"categories":[],"categories_nodes":[],"categories_segments":[],"categories_sizes":[],"default_left":[true,true,true,false,true,false,true,false,false,false,false],"id":20,"left_children":[1,3,5,-1,7,-1,9,-1,-1,-1,-1],"loss_changes":[5.1458454E-1,3.002969E-1,1.2393761E-1,0E0,1.4015049E-2,0E0,1.6163039E-1,0E0,0E0,0E0,0E0],"parents":[2147483647,0,0,1,1,2,2,4,4,6,6],"right_children":[2,4,6,-1,8,-1,10,-1,-1,-1,-1],"split_conditions":[1.25E2,3.5E3,1.75E2,1.6374756E-1,6.5E3,2.2498523E-1,6.5E3,3.1737674E-2,7.2078705E-2,1.0013581E-1,2.0757523E-1],"split_indices":[1,0,1,0,0,0,0,0,0,0,0],"split_type":[0,0,0,0,0,0,0,0,0,0,0],"sum_hessian":[3.7E1,1.3E1,2.4E1,4E0,9E0,1.2E1,1.2E1,4E0,5E0,9E0,3E0],"tree_param":{"num_deleted":"0","num_feature":"4","num_nodes":"11","size_leaf_vector":"0"}},{"base_weights":[3.9969876E-1,2.5409046E-1,4.6525148E-1,4.1481933E-1,1.4831695E-1,5.3081894E-1,3.1381837E-1,8.0401614E-2,1.8019359E-1,3.4980264E-1,6.681099E-1,1.789978E-1,3.7386575E-1],"categories":[],"categories_nodes":[],"categories_segments":[],"categories_sizes":[],"default_left":[true,true,true,false,true,true,true,false,false,false,false,false,false],"id":21,"left_children":[1,3,5,-1,7,9,11,-1,-1,-1,-1,-1,-1],"loss_changes":[2.4449492E-1,1.764872E-1,8.1645966E-2,0E0,7.1612597E-3,1.6392422E-1,1.4035106E-2,0E0,0E0,0E0,0E0,0E0,0E0],"parents":[2147483647,0,0,1,1,2,2,4,4,5,5,6,6],"right_children":[2,4,6,-1,8,10,12,-1,-1,-1,-1,-1,-1],"split_conditions":[1.25E2,3.5E3,1.2E3,1.244458E-1,6.5E3,6E2,3.5E3,2.4120485E-2,5.405808E-2,1.04940794E-1,2.0043297E-1,5.369934E-2,1.1215973E-1],"split_indices":[1,0,2,0,0,2,0,0,0,0,0,0,0],"split_type":[0,0,0,0,0,0,0,0,0,0,0,0,0],"sum_hessian":[3.7E1,1.3E1,2.4E1,4E0,9E0,1.5E1,9E0,4E0,5E0,8E0,7E0,4E0,5E0],"tree_param":{"num_deleted":"0","num_feature":"4","num_nodes":"13","size_leaf_vector":"0"}},{"base_weights":[2.9752108E-1,1.9234249E-1,3.4452027E-1,3.152588E-1,1.1165009E-1,4.1325262E-1,2.4928635E-1,6.11145E-2,1.3515472E-1,1.697113E-1,3.859024E-1],"categories":[],"categories_nodes":[],"categories_segments":[],"categories_sizes":[],"default_left":[true,true,true,false,true,false,true,false,false,false,false],"id":22,"left_children":[1,3,5,-1,7,-1,9,-1,-1,-1,-1],"loss_changes":[1.2157965E-1,1.0365909E-1,6.062317E-2,0E0,3.6182925E-3,0E0,7.5833976E-2,0E0,0E0,0E0,0E0],"parents":[2147483647,0,0,1,1,2,2,4,4,6,6],"right_children":[2,4,6,-1,8,-1,10,-1,-1,-1,-1],"split_conditions":[1.25E2,3.5E3,1.75E2,9.457765E-2,6.5E3,1.2397579E-1,6.5E3,1.8334351E-2,4.0546417E-2,5.0913393E-2,1.1577073E-1],"split_indices":[1,0,1,0,0,0,0,0,0,0,0],"split_type":[0,0,0,0,0,0,0,0,0,0,0],"sum_hessian":[3.7E1,1.3E1,2.4E1,4E0,9E0,1.2E1,1.2E1,4E0,5E0,9E0,3E0],"tree_param":{"num_deleted":"0","num_feature":"4","num_nodes":"11","size_leaf_vector":"0"}},{"base_weights":[2.1995585E-1,2.5879288E-1,1.4315288E-1,3.4448242E-1,1.9441795E-1,9.9465944E-2,3.022897E-1,4.6441652E-2,1.270752E-1],"categories":[],"categories_nodes":[],"categories_segments":[],"categories_sizes":[],"default_left":[true,true,false,false,true,true,false,false,false],"id":23,"left_children":[1,3,-1,-1,5,7,-1,-1,-1],"loss_changes":[7.629943E-2,6.5416574E-2,0E0,0E0,1.3381463E-1,8.738026E-3,0E0,0E0,0E0],"parents":[2147483647,0,0,1,1,4,4,5,5],"right_children":[2,4,-1,-1,6,8,-1,-1,-1],"split_conditions":[1.2E3,3.5E3,4.2945866E-2,1.0334473E-1,6.5E3,1.5E2,9.068691E-2,1.3932496E-2,3.812256E-2],"split_indices":[2,0,0,0,0,1,0,0,0],"split_type":[0,0,0,0,0,0,0,0,0],"sum_hessian":[3.7E1,2.3E1,1.4E1,8E0,1.5E1,9E0,6E0,4E0,5E0],"tree_param":{"num_deleted":"0","num_feature":"4","num_nodes":"9","size_leaf_vector":"0"}},{"base_weights":[1.6157813E-1,9.675271E-2,1.9141723E-1,1.5693359E-1,5.6987E-2,2.2704506E-1,1.15270995E-1,1.3550483E-1,3.016472E-1,6.095581E-2,1.4132182E-1],"categories":[],"categories_nodes":[],"categories_segments":[],"categories_sizes":[],"default_left":[true,true,true,false,false,true,true,false,false,false,false],"id":24,"left_children":[1,3,5,-1,-1,7,9,-1,-1,-1,-1],"loss_changes":[5.498451E-2,2.4560735E-2,4.1651428E-2,0E0,0E0,6.8390906E-2,5.5351704E-3,0E0,0E0,0E0,0E0],"parents":[2147483647,0,0,1,1,2,2,5,5,6,6],"right_children":[2,4,6,-1,-1,8,10,-1,-1,-1,-1],"split_conditions":[1.25E2,3.5E3,1.2E3,4.708008E-2,1.70961E-2,6E2,3.5E3,4.0651448E-2,9.0494156E-2,1.8286744E-2,4.239655E-2],"split_indices":[1,0,2,0,0,2,0,0,0,0,0],"split_type":[0,0,0,0,0,0,0,0,0,0,0],"sum_hessian":[3.7E1,1.3E1,2.4E1,4E0,9E0,1.5E1,9E0,8E0,7E0,4E0,5E0],"tree_param":{"num_deleted":"0","num_feature":"4","num_nodes":"11","size_leaf_vector":"0"}},{"base_weights":[1.1984614E-1,7.231249E-2,1.4167114E-1,1.19262695E-1,4.160614E-2,1.760606E-1,9.63839E-2,2.161255E-2,5.133311E-2,2.0660019E-1,1.0599772E-1,6.0028076E-2,1.6317749E-1],"categories":[],"categories_nodes":[],"categories_segments":[],"categories_sizes":[],"default_left":[true,true,true,false,true,true,true,false,false,false,false,false,false],"id":25,"left_children":[1,3,5,-1,7,9,11,-1,-1,-1,-1,-1,-1],"loss_changes":[2.9177427E-2,1.5221313E-2,2.1965683E-2,0E0,8.3533116E-4,5.916834E-3,2.1773122E-2,0E0,0E0,0E0,0E0,0E0,0E0],"parents":[2147483647,0,0,1,1,2,2,4,4,5,5,6,6],"right_children":[2,4,6,-1,8,10,12,-1,-1,-1,-1,-1,-1],"split_conditions":[1.25E2,3.5E3,1.75E2,3.577881E-2,6.5E3,1.2E3,6.5E3,6.483765E-3,1.5399934E-2,6.1980058E-2,3.1799316E-2,1.8008424E-2,4.895325E-2],"split_indices":[1,0,1,0,0,2,0,0,0,0,0,0,0],"split_type":[0,0,0,0,0,0,0,0,0,0,0,0,0],"sum_hessian":[3.7E1,1.3E1,2.4E1,4E0,9E0,1.2E1,1.2E1,4E0,5E0,7E0,5E0,9E0,3E0],"tree_param":{"num_deleted":"0","num_feature":"4","num_nodes":"13","size_leaf_vector":"0"}},{"base_weights":[8.964177E-2,1.04621604E-1,4.8467E-2,1.4804417E-1,7.854662E-2,2.6869033E-2,8.494568E-2,1.09205455E-1,4.6321522E-2],"categories":[],"categories_nodes":[],"categories_segments":[],"categories_sizes":[],"default_left":[true,true,true,false,true,false,false,false,false],"id":26,"left_children":[1,3,5,-1,7,-1,-1,-1,-1],"loss_changes":[1.836735E-2,1.8942177E-2,7.1719736E-3,0E0,1.3713144E-2,0E0,0E0,0E0,0E0],"parents":[2147483647,0,0,1,1,2,2,4,4],"right_children":[2,4,6,-1,8,-1,-1,-1,-1],"split_conditions":[1.1E-1,3.5E3,6.5E3,4.4413254E-2,9E-2,8.0607105E-3,2.5483705E-2,3.2761637E-2,1.3896457E-2],"split_indices":[3,0,0,0,3,0,0,0,0],"split_type":[0,0,0,0,0,0,0,0,0],"sum_hessian":[3.7E1,2.6E1,1.1E1,8E0,1.8E1,8E0,3E0,8E0,1E1],"tree_param":{"num_deleted":"0","num_feature":"4","num_nodes":"9","size_leaf_vector":"0"}},{"base_weights":[6.6031605E-2,3.479331E-2,8.0883786E-2,5.5126954E-2,2.1147156E-2,9.884834E-2,4.4052124E-2,9.991455E-3,2.6919046E-2,5.250041E-2,1.3863373E-1,2.5482178E-2,5.218506E-2],"categories":[],"categories_nodes":[],"categories_segments":[],"categories_sizes":[],"default_left":[true,true,true,false,true,true,true,false,false,false,false,false,false],"id":27,"left_children":[1,3,5,-1,7,9,11,-1,-1,-1,-1,-1,-1],"loss_changes":[1.481615E-2,2.7188864E-3,1.2187138E-2,0E0,3.7493464E-4,2.2225201E-2,1.8049218E-4,0E0,0E0,0E0,0E0,0E0,0E0],"parents":[2147483647,0,0,1,1,2,2,4,4,5,5,6,6],"right_children":[2,4,6,-1,8,10,12,-1,-1,-1,-1,-1,-1],"split_conditions":[1.25E2,3.5E3,1.2E3,1.6538087E-2,6.5E3,6E2,3.5E3,2.9974366E-3,8.075714E-3,1.5750123E-2,4.159012E-2,7.644654E-3,1.5655518E-2],"split_indices":[1,0,2,0,0,2,0,0,0,0,0,0,0],"split_type":[0,0,0,0,0,0,0,0,0,0,0,0,0],"sum_hessian":[3.7E1,1.3E1,2.4E1,4E0,9E0,1.5E1,9E0,4E0,5E0,8E0,7E0,4E0,5E0],"tree_param":{"num_deleted":"0","num_feature":"4","num_nodes":"13","size_leaf_vector":"0"}},{"base_weights":[4.9067847E-2,2.632468E-2,5.984131E-2,4.1894533E-2,1.5907288E-2,7.2776794E-2,3.31604E-2,7.598877E-3,2.0179749E-2,3.850301E-2,1.022377E-1,1.9354248E-2,3.9138794E-2,2.1738688E-2,5.4023743E-2],"categories":[],"categories_nodes":[],"categories_segments":[],"categories_sizes":[],"default_left":[true,true,true,false,true,true,true,false,false,true,false,false,false,false,false],"id":28,"left_children":[1,3,5,-1,7,9,11,-1,-1,13,-1,-1,-1,-1,-1],"loss_changes":[7.7355504E-3,1.6043326E-3,6.2149614E-3,0E0,2.016304E-4,1.2219332E-2,6.78841E-5,0E0,0E0,1.1673458E-3,0E0,0E0,0E0,0E0,0E0],"parents":[2147483647,0,0,1,1,2,2,4,4,5,5,6,6,9,9],"right_children":[2,4,6,-1,8,10,12,-1,-1,14,-1,-1,-1,-1,-1],"split_conditions":[1.25E2,3.5E3,1.2E3,1.256836E-2,6.5E3,6E2,3.5E3,2.2796632E-3,6.053925E-3,6.5E3,3.0671312E-2,5.8062747E-3,1.1741639E-2,6.5216064E-3,1.6207123E-2],"split_indices":[1,0,2,0,0,2,0,0,0,0,0,0,0,0,0],"split_type":[0,0,0,0,0,0,0,0,0,0,0,0,0,0,0],"sum_hessian":[3.7E1,1.3E1,2.4E1,4E0,9E0,1.5E1,9E0,4E0,5E0,8E0,7E0,4E0,5E0,5E0,3E0],"tree_param":{"num_deleted":"0","num_feature":"4","num_nodes":"15","size_leaf_vector":"0"}},{"base_weights":[3.6763642E-2,1.992035E-2,4.4725344E-2,3.1835936E-2,1.197052E-2,5.8157112E-2,2.785316E-2,5.7678223E-3,1.5144348E-2,7.249451E-2,2.9347738E-2,1.713562E-2,4.7683716E-2],"categories":[],"categories_nodes":[],"categories_segments":[],"categories_sizes":[],"default_left":[true,true,true,false,true,true,true,false,false,false,false,false,false],"id":29,"left_children":[1,3,5,-1,7,9,11,-1,-1,-1,-1,-1,-1],"loss_changes":[4.204903E-3,9.4508333E-4,4.045721E-3,0E0,1.0951306E-4,3.2421164E-3,1.9458625E-3,0E0,0E0,0E0,0E0,0E0,0E0],"parents":[2147483647,0,0,1,1,2,2,4,4,5,5,6,6],"right_children":[2,4,6,-1,8,10,12,-1,-1,-1,-1,-1,-1],"split_conditions":[1.25E2,3.5E3,1.75E2,9.550781E-3,6.5E3,1.2E3,6.5E3,1.7303467E-3,4.5433044E-3,2.1748353E-2,8.804322E-3,5.1406864E-3,1.4305116E-2],"split_indices":[1,0,1,0,0,2,0,0,0,0,0,0,0],"split_type":[0,0,0,0,0,0,0,0,0,0,0,0,0],"sum_hessian":[3.7E1,1.3E1,2.4E1,4E0,9E0,1.2E1,1.2E1,4E0,5E0,7E0,5E0,9E0,3E0],"tree_param":{"num_deleted":"0","num_feature":"4","num_nodes":"13","size_leaf_vector":"0"}},{"base_weights":[2.7463812E-2,1.5070234E-2,3.3305664E-2,2.4194336E-2,9.00116E-3,4.3048564E-2,2.100079E-2,4.3762205E-3,1.13550825E-2,6.508789E-2,2.6021322E-2,1.2521362E-2,3.6949158E-2],"categories":[],"categories_nodes":[],"categories_segments":[],"categories_sizes":[],"default_left":[true,true,true,false,true,true,true,false,false,false,false,false,false],"id":30,"left_children":[1,3,5,-1,7,9,11,-1,-1,-1,-1,-1,-1],"loss_changes":[2.2493303E-3,5.5747083E-4,2.0930748E-3,0E0,5.917519E-5,3.1848252E-3,1.2953752E-3,0E0,0E0,0E0,0E0,0E0,0E0],"parents":[2147483647,0,0,1,1,2,2,4,4,5,5,6,6],"right_children":[2,4,6,-1,8,10,12,-1,-1,-1,-1,-1,-1],"split_conditions":[1.25E2,3.5E3,1.75E2,7.258301E-3,6.5E3,3.5E3,6.5E3,1.3128662E-3,3.406525E-3,1.9526368E-2,7.806397E-3,3.7564088E-3,1.10847475E-2],"split_indices":[1,0,1,0,0,0,0,0,0,0,0,0,0],"split_type":[0,0,0,0,0,0,0,0,0,0,0,0,0],"sum_hessian":[3.7E1,1.3E1,2.4E1,4E0,9E0,1.2E1,1.2E1,4E0,5E0,4E0,8E0,9E0,3E0],"tree_param":{"num_deleted":"0","num_feature":"4","num_nodes":"13","size_leaf_vector":"0"}},{"base_weights":[2.064715E-2,1.1399405E-2,2.5E-2,1.838379E-2,6.767273E-3,3.087616E-2,1.3098145E-2,3.326416E-3,8.506775E-3,1.4682346E-2,4.523468E-2,7.611084E-3,1.5487671E-2,8.895874E-3,1.9691467E-2],"categories":[],"categories_nodes":[],"categories_segments":[],"categories_sizes":[],"default_left":[true,true,true,false,true,true,true,false,false,true,false,false,false,false,false],"id":31,"left_children":[1,3,5,-1,7,9,11,-1,-1,13,-1,-1,-1,-1,-1],"loss_changes":[1.2446679E-3,3.2852823E-4,1.3440102E-3,0E0,3.15567E-5,3.0561564E-3,1.3236771E-5,0E0,0E0,8.5693435E-5,0E0,0E0,0E0,0E0,0E0],"parents":[2147483647,0,0,1,1,2,2,4,4,5,5,6,6,9,9],"right_children":[2,4,6,-1,8,10,12,-1,-1,14,-1,-1,-1,-1,-1],"split_conditions":[1.25E2,3.5E3,1.2E3,5.515137E-3,6.5E3,6E2,3.5E3,9.979248E-4,2.5520325E-3,6.5E3,1.3570405E-2,2.2833252E-3,4.6463013E-3,2.6687623E-3,5.9074406E-3],"split_indices":[1,0,2,0,0,2,0,0,0,0,0,0,0,0,0],"split_type":[0,0,0,0,0,0,0,0,0,0,0,0,0,0,0],"sum_hessian":[3.7E1,1.3E1,2.4E1,4E0,9E0,1.5E1,9E0,4E0,5E0,8E0,7E0,4E0,5E0,5E0,3E0],"tree_param":{"num_deleted":"0","num_feature":"4","num_nodes":"15","size_leaf_vector":"0"}},{"base_weights":[1.5452736E-2,2.243981E-2,1.1364863E-2,2.9201932E-2,5.780029E-3,5.0827027E-3,1.4391731E-2,1.3964844E-2,3.8598634E-2,2.520752E-3,6.3705444E-3,9.984797E-3,1.9260952E-2],"categories":[],"categories_nodes":[],"categories_segments":[],"categories_sizes":[],"default_left":[true,true,true,true,false,true,true,false,false,false,false,false,false],"id":32,"left_children":[1,3,5,7,-1,9,11,-1,-1,-1,-1,-1,-1],"loss_changes":[8.303402E-4,1.2957333E-3,4.2124814E-4,7.495815E-4,0E0,1.6935315E-5,1.7247489E-4,0E0,0E0,0E0,0E0,0E0,0E0],"parents":[2147483647,0,0,1,1,2,2,3,3,5,5,6,6],"right_children":[2,4,6,8,-1,10,12,-1,-1,-1,-1,-1,-1],"split_conditions":[3.5E3,1.75E2,1.25E2,1.25E2,1.7340088E-3,6.5E3,6.5E3,4.1894536E-3,1.1579591E-2,7.562256E-4,1.9111634E-3,2.995439E-3,5.7782857E-3],"split_indices":[0,1,1,1,0,0,0,0,0,0,0,0,0],"split_type":[0,0,0,0,0,0,0,0,0,0,0,0,0],"sum_hessian":[3.7E1,1.2E1,2.5E1,8E0,4E0,9E0,1.6E1,4E0,4E0,4E0,5E0,1E1,6E0],"tree_param":{"num_deleted":"0","num_feature":"4","num_nodes":"13","size_leaf_vector":"0"}},{"base_weights":[1.15810195E-2,1.7059326E-2,8.396442E-3,2.2203233E-2,4.388428E-3,3.8162232E-3,1.059678E-2,1.0620117E-2,2.9345702E-2,1.9104003E-3,4.7683716E-3,7.265958E-3,1.4317104E-2,9.129842E-3,4.1910806E-3],"categories":[],"categories_nodes":[],"categories_segments":[],"categories_sizes":[],"default_left":[true,true,true,true,false,true,true,false,false,false,false,true,false,false,false],"id":33,"left_children":[1,3,5,7,-1,9,11,-1,-1,-1,-1,13,-1,-1,-1],"loss_changes":[5.1971385E-4,7.498758E-4,2.2158911E-4,4.3293368E-4,0E0,9.036754E-6,1.0663201E-4,0E0,0E0,0E0,0E0,2.4779525E-5,0E0,0E0,0E0],"parents":[2147483647,0,0,1,1,2,2,3,3,5,5,6,6,11,11],"right_children":[2,4,6,8,-1,10,12,-1,-1,-1,-1,14,-1,-1,-1],"split_conditions":[3.5E3,1.75E2,1.25E2,1.25E2,1.3165284E-3,6.5E3,6.5E3,3.1860352E-3,8.803711E-3,5.7312014E-4,1.4305115E-3,1.75E2,4.295131E-3,2.7389526E-3,1.2573242E-3],"split_indices":[0,1,1,1,0,0,0,0,0,0,0,1,0,0,0],"split_type":[0,0,0,0,0,0,0,0,0,0,0,0,0,0,0],"sum_hessian":[3.7E1,1.2E1,2.5E1,8E0,4E0,9E0,1.6E1,4E0,4E0,4E0,5E0,1E1,6E0,5E0,5E0],"tree_param":{"num_deleted":"0","num_feature":"4","num_nodes":"15","size_leaf_vector":"0"}},{"base_weights":[8.728429E-3,1.29746655E-2,6.2696016E-3,1.6886393E-2,3.338623E-3,2.8671264E-3,7.902257E-3,8.081054E-3,2.2314453E-2,1.4465332E-3,3.5730998E-3,5.448775E-3,1.0628836E-2,6.841024E-3,3.1483967E-3],"categories":[],"categories_nodes":[],"categories_segments":[],"categories_sizes":[],"default_left":[true,true,true,true,false,true,true,false,false,false,false,true,false,false,false],"id":34,"left_children":[1,3,5,7,-1,9,11,-1,-1,-1,-1,13,-1,-1,-1],"loss_changes":[3.154031E-4,4.3363916E-4,1.2177497E-4,2.4983892E-4,0E0,4.860398E-6,5.580939E-5,0E0,0E0,0E0,0E0,1.3691402E-5,0E0,0E0,0E0],"parents":[2147483647,0,0,1,1,2,2,3,3,5,5,6,6,11,11],"right_children":[2,4,6,8,-1,10,12,-1,-1,-1,-1,14,-1,-1,-1],"split_conditions":[3.5E3,1.75E2,1.25E2,1.25E2,1.001587E-3,6.5E3,6.5E3,2.4243165E-3,6.6943364E-3,4.3396E-4,1.07193E-3,1.75E2,3.188651E-3,2.0523074E-3,9.4451907E-4],"split_indices":[0,1,1,1,0,0,0,0,0,0,0,1,0,0,0],"split_type":[0,0,0,0,0,0,0,0,0,0,0,0,0,0,0],"sum_hessian":[3.7E1,1.2E1,2.5E1,8E0,4E0,9E0,1.6E1,4E0,4E0,4E0,5E0,1E1,6E0,5E0,5E0],"tree_param":{"num_deleted":"0","num_feature":"4","num_nodes":"15","size_leaf_vector":"0"}},{"base_weights":[6.5849707E-3,9.866567E-3,4.6909037E-3,1.2844509E-2,2.532959E-3,7.212321E-3,3.1695897E-3,6.152344E-3,1.6967773E-2,1.9683838E-3,4.152086E-3,2.6830037E-3,5.317688E-3],"categories":[],"categories_nodes":[],"categories_segments":[],"categories_sizes":[],"default_left":[true,true,true,true,false,false,true,false,false,false,true,false,false],"id":35,"left_children":[1,3,5,7,-1,-1,9,-1,-1,-1,11,-1,-1],"loss_changes":[1.8990843E-4,2.5137316E-4,7.687247E-5,1.4395046E-4,0E0,0E0,1.3070356E-5,0E0,0E0,7.7520235E-7,1.1439115E-6,0E0,0E0],"parents":[2147483647,0,0,1,1,2,2,3,3,6,6,10,10],"right_children":[2,4,6,8,-1,-1,10,-1,-1,-1,12,-1,-1],"split_conditions":[3.5E3,1.75E2,9E-2,1.25E2,7.5988774E-4,2.1636963E-3,6.5E3,1.8457032E-3,5.090332E-3,5.9051515E-4,1.25E2,8.049011E-4,1.5953064E-3],"split_indices":[0,1,3,1,0,0,0,0,0,0,1,0,0],"split_type":[0,0,0,0,0,0,0,0,0,0,0,0,0],"sum_hessian":[3.7E1,1.2E1,2.5E1,8E0,4E0,8E0,1.7E1,4E0,4E0,9E0,8E0,5E0,3E0],"tree_param":{"num_deleted":"0","num_feature":"4","num_nodes":"13","size_leaf_vector":"0"}},{"base_weights":[4.9522803E-3,7.5002816E-3,3.487807E-3,9.765625E-3,1.9226074E-3,1.5335083E-3,4.4322293E-3,4.6875E-3,1.2890625E-2,6.4086914E-4,2.0217896E-3,2.8409092E-3,6.2997E-3],"categories":[],"categories_nodes":[],"categories_segments":[],"categories_sizes":[],"default_left":[true,true,true,true,false,true,true,false,false,false,false,false,false],"id":36,"left_children":[1,3,5,7,-1,9,11,-1,-1,-1,-1,-1,-1],"loss_changes":[1.15636736E-4,1.4548405E-4,4.1190913E-5,8.2397484E-5,0E0,3.0628871E-6,3.2622775E-5,0E0,0E0,0E0,0E0,0E0,0E0],"parents":[2147483647,0,0,1,1,2,2,3,3,5,5,6,6],"right_children":[2,4,6,8,-1,10,12,-1,-1,-1,-1,-1,-1],"split_conditions":[3.5E3,1.75E2,1.25E2,1.25E2,5.767823E-4,6.5E3,6.5E3,1.40625E-3,3.8671875E-3,1.9226075E-4,6.0653687E-4,8.522728E-4,1.8899101E-3],"split_indices":[0,1,1,1,0,0,0,0,0,0,0,0,0],"split_type":[0,0,0,0,0,0,0,0,0,0,0,0,0],"sum_hessian":[3.7E1,1.2E1,2.5E1,8E0,4E0,9E0,1.6E1,4E0,4E0,4E0,5E0,1E1,6E0],"tree_param":{"num_deleted":"0","num_feature":"4","num_nodes":"13","size_leaf_vector":"0"}},{"base_weights":[3.7123028E-3,5.697397E-3,2.5769747E-3,7.4191624E-3,1.4587402E-3,4.180908E-3,1.6318427E-3,3.5644532E-3,9.790039E-3,2.6194255E-3,5.4779053E-3,9.460449E-4,2.2125244E-3],"categories":[],"categories_nodes":[],"categories_segments":[],"categories_sizes":[],"default_left":[true,true,true,true,false,true,true,false,false,false,false,false,false],"id":37,"left_children":[1,3,5,7,-1,9,11,-1,-1,-1,-1,-1,-1],"loss_changes":[7.0959795E-5,8.405102E-5,3.259156E-5,4.735519E-5,0E0,3.8781873E-6,5.074995E-6,0E0,0E0,0E0,0E0,4.1198655E-7,0E0],"parents":[2147483647,0,0,1,1,2,2,3,3,5,5,6,6],"right_children":[2,4,6,8,-1,10,12,-1,-1,-1,-1,-1,-1],"split_conditions":[3.5E3,1.75E2,9E-2,1.25E2,4.3762207E-4,6.5E3,6.5E3,1.069336E-3,2.9370117E-3,7.858277E-4,1.6433717E-3,2.8381348E-4,6.637573E-4],"split_indices":[0,1,3,1,0,0,0,0,0,0,0,0,0],"split_type":[0,0,0,0,0,0,0,0,0,0,0,0,0],"sum_hessian":[3.7E1,1.2E1,2.5E1,8E0,4E0,8E0,1.7E1,4E0,4E0,5E0,3E0,9E0,8E0],"tree_param":{"num_deleted":"0","num_feature":"4","num_nodes":"13","size_leaf_vector":"0"}},{"base_weights":[2.8056095E-3,4.3358435E-3,1.9325843E-3,5.642361E-3,1.1169433E-3,3.1907824E-3,1.1961195E-3,2.709961E-3,7.446289E-3,1.9582112E-3,4.2419434E-3,6.988525E-4,1.6157362E-3,9.536743E-4,2.204895E-3],"categories":[],"categories_nodes":[],"categories_segments":[],"categories_sizes":[],"default_left":[true,true,true,true,false,true,true,false,false,false,false,false,true,false,false],"id":38,"left_children":[1,3,5,7,-1,9,11,-1,-1,-1,-1,-1,13,-1,-1],"loss_changes":[4.2386062E-5,4.8369984E-5,2.0275525E-5,2.742937E-5,0E0,3.354049E-6,2.6267462E-6,0E0,0E0,0E0,0E0,7.4837953E-7,1.407785E-6,0E0,0E0],"parents":[2147483647,0,0,1,1,2,2,3,3,5,5,6,6,12,12],"right_children":[2,4,6,8,-1,10,12,-1,-1,-1,-1,-1,14,-1,-1],"split_conditions":[3.5E3,1.75E2,9E-2,1.25E2,3.35083E-4,6.5E3,6.5E3,8.129883E-4,2.2338869E-3,5.874634E-4,1.272583E-3,2.0965577E-4,1.25E2,2.861023E-4,6.6146854E-4],"split_indices":[0,1,3,1,0,0,0,0,0,0,0,0,1,0,0],"split_type":[0,0,0,0,0,0,0,0,0,0,0,0,0,0,0],"sum_hessian":[3.7E1,1.2E1,2.5E1,8E0,4E0,8E0,1.7E1,4E0,4E0,5E0,3E0,9E0,8E0,5E0,3E0],"tree_param":{"num_deleted":"0","num_feature":"4","num_nodes":"15","size_leaf_vector":"0"}},{"base_weights":[2.1318134E-3,3.293551E-3,1.4689519E-3,4.2860243E-3,8.4838865E-4,2.4414062E-3,9.011163E-4,2.0507812E-3,5.6640627E-3,1.4750162E-3,3.2806396E-3,4.8675537E-4,1.2613932E-3],"categories":[],"categories_nodes":[],"categories_segments":[],"categories_sizes":[],"default_left":[true,true,true,true,false,true,true,false,false,false,false,false,false],"id":39,"left_children":[1,3,5,7,-1,9,11,-1,-1,-1,-1,-1,-1],"loss_changes":[2.4424633E-5,2.791165E-5,1.2157059E-5,1.6106496E-5,0E0,2.460245E-6,2.073135E-6,0E0,0E0,0E0,0E0,8.364675E-7,7.044682E-7],"parents":[2147483647,0,0,1,1,2,2,3,3,5,5,6,6],"right_children":[2,4,6,8,-1,10,12,-1,-1,-1,-1,-1,-1],"split_conditions":[3.5E3,1.75E2,9E-2,1.25E2,2.545166E-4,6.5E3,1.25E2,6.1523437E-4,1.6992189E-3,4.4250488E-4,9.841919E-4,1.4602662E-4,3.78418E-4],"split_indices":[0,1,3,1,0,0,1,0,0,0,0,0,0],"split_type":[0,0,0,0,0,0,0,0,0,0,0,0,0],"sum_hessian":[3.7E1,1.2E1,2.5E1,8E0,4E0,8E0,1.7E1,4E0,4E0,5E0,3E0,9E0,8E0],"tree_param":{"num_deleted":"0","num_feature":"4","num_nodes":"13","size_leaf_vector":"0"}},{"base_weights":[1.615424E-3,2.5047888E-3,1.1086097E-3,3.2552083E-3,6.5307616E-4,1.8785265E-3,6.620619E-4,1.5625E-3,4.296875E-3,1.1189779E-3,2.5482178E-3,2.6245118E-4,1.0325114E-3],"categories":[],"categories_nodes":[],"categories_segments":[],"categories_sizes":[],"default_left":[true,true,true,true,false,true,true,false,false,false,false,false,false],"id":40,"left_children":[1,3,5,7,-1,9,11,-1,-1,-1,-1,-1,-1],"loss_changes":[1.4351397E-5,1.5938393E-5,7.69522E-6,9.155279E-6,0E0,1.7265702E-6,2.3936564E-6,0E0,0E0,0E0,0E0,5.4237125E-7,6.9014914E-7],"parents":[2147483647,0,0,1,1,2,2,3,3,5,5,6,6],"right_children":[2,4,6,8,-1,10,12,-1,-1,-1,-1,-1,-1],"split_conditions":[3.5E3,1.75E2,9E-2,1.25E2,1.9592285E-4,6.5E3,6.5E3,4.6875002E-4,1.2890626E-3,3.356934E-4,7.6446537E-4,7.873536E-5,3.097534E-4],"split_indices":[0,1,3,1,0,0,0,0,0,0,0,0,0],"split_type":[0,0,0,0,0,0,0,0,0,0,0,0,0],"sum_hessian":[3.7E1,1.2E1,2.5E1,8E0,4E0,8E0,1.7E1,4E0,4E0,5E0,3E0,9E0,8E0],"tree_param":{"num_deleted":"0","num_feature":"4","num_nodes":"13","size_leaf_vector":"0"}},{"base_weights":[1.2227108E-3,1.9132174E-3,8.3043025E-4,2.4820964E-3,5.065918E-4,1.6021729E-4,1.1758243E-3,1.1962891E-3,3.2714843E-3,6.630637E-4,1.813616E-3],"categories":[],"categories_nodes":[],"categories_segments":[],"categories_sizes":[],"default_left":[true,true,true,true,false,false,true,false,false,false,false],"id":41,"left_children":[1,3,5,7,-1,-1,9,-1,-1,-1,-1],"loss_changes":[8.704352E-6,9.1451875E-6,5.8302903E-6,5.2213654E-6,0E0,4.924368E-7,4.3570417E-6,0E0,0E0,2.3967414E-7,0E0],"parents":[2147483647,0,0,1,1,2,2,3,3,6,6],"right_children":[2,4,6,8,-1,-1,10,-1,-1,-1,-1],"split_conditions":[3.5E3,1.75E2,1.25E2,1.25E2,1.5197755E-4,4.8065187E-5,6.5E3,3.5888673E-4,9.814453E-4,1.9891912E-4,5.440848E-4],"split_indices":[0,1,1,1,0,0,0,0,0,0,0],"split_type":[0,0,0,0,0,0,0,0,0,0,0],"sum_hessian":[3.7E1,1.2E1,2.5E1,8E0,4E0,9E0,1.6E1,4E0,4E0,1E1,6E0],"tree_param":{"num_deleted":"0","num_feature":"4","num_nodes":"11","size_leaf_vector":"0"}},{"base_weights":[9.0789795E-4,1.4531062E-3,6.0037465E-4,1.8853082E-3,3.845215E-4,1.135932E-3,2.992418E-4,9.033203E-4,2.4902343E-3,4.8828126E-5,5.4423016E-4],"categories":[],"categories_nodes":[],"categories_segments":[],"categories_sizes":[],"default_left":[true,true,true,true,false,false,true,false,false,false,false],"id":42,"left_children":[1,3,5,7,-1,-1,9,-1,-1,-1,-1],"loss_changes":[5.498834E-6,5.2790365E-6,3.8532035E-6,3.096793E-6,0E0,7.9485835E-7,1.0776981E-6,0E0,0E0,3.1078233E-7,3.1761988E-7],"parents":[2147483647,0,0,1,1,2,2,3,3,6,6],"right_children":[2,4,6,8,-1,-1,10,-1,-1,-1,-1],"split_conditions":[3.5E3,1.75E2,9E-2,1.25E2,1.1535645E-4,3.4077963E-4,6.5E3,2.709961E-4,7.4707036E-4,1.4648438E-5,1.6326905E-4],"split_indices":[0,1,3,1,0,0,0,0,0,0,0],"split_type":[0,0,0,0,0,0,0,0,0,0,0],"sum_hessian":[3.7E1,1.2E1,2.5E1,8E0,4E0,8E0,1.7E1,4E0,4E0,9E0,8E0],"tree_param":{"num_deleted":"0","num_feature":"4","num_nodes":"11","size_leaf_vector":"0"}},{"base_weights":[6.8624393E-4,1.1056754E-3,4.5013428E-4,1.437717E-3,2.8686522E-4,2.8991699E-5,6.713867E-4,6.8359374E-4,1.9042969E-3,3.1627307E-4,1.13351E-3],"categories":[],"categories_nodes":[],"categories_segments":[],"categories_sizes":[],"default_left":[true,true,true,true,false,false,true,false,false,false,false],"id":43,"left_children":[1,3,5,7,-1,-1,9,-1,-1,-1,-1],"loss_changes":[3.2655062E-6,3.1219988E-6,2.4031851E-6,1.8649644E-6,0E0,2.5408033E-7,2.4313085E-6,0E0,0E0,8.889856E-9,0E0],"parents":[2147483647,0,0,1,1,2,2,3,3,6,6],"right_children":[2,4,6,8,-1,-1,10,-1,-1,-1,-1],"split_conditions":[3.5E3,1.75E2,1.25E2,1.25E2,8.605957E-5,8.69751E-6,6.5E3,2.0507813E-4,5.712891E-4,9.488193E-5,3.4005303E-4],"split_indices":[0,1,1,1,0,0,0,0,0,0,0],"split_type":[0,0,0,0,0,0,0,0,0,0,0],"sum_hessian":[3.7E1,1.2E1,2.5E1,8E0,4E0,9E0,1.6E1,4E0,4E0,1E1,6E0],"tree_param":{"num_deleted":"0","num_feature":"4","num_nodes":"11","size_leaf_vector":"0"}},{"base_weights":[5.15988E-4,8.333646E-4,3.37454E-4,1.0850695E-3,2.1362305E-4,6.7477755E-4,1.5004475E-4,5.126953E-4,1.4404297E-3],"categories":[],"categories_nodes":[],"categories_segments":[],"categories_sizes":[],"default_left":[true,true,true,true,false,false,false,false,false],"id":44,"left_children":[1,3,5,7,-1,-1,-1,-1,-1],"loss_changes":[1.8719529E-6,1.7960992E-6,1.5424098E-6,1.0920903E-6,0E0,9.593914E-7,3.8712233E-7,0E0,0E0],"parents":[2147483647,0,0,1,1,2,2,3,3],"right_children":[2,4,6,8,-1,-1,-1,-1,-1],"split_conditions":[3.5E3,1.75E2,9E-2,1.25E2,6.408692E-5,2.0243328E-4,4.501343E-5,1.5380859E-4,4.3212893E-4],"split_indices":[0,1,3,1,0,0,0,0,0],"split_type":[0,0,0,0,0,0,0,0,0],"sum_hessian":[3.7E1,1.2E1,2.5E1,8E0,4E0,8E0,1.7E1,4E0,4E0],"tree_param":{"num_deleted":"0","num_feature":"4","num_nodes":"9","size_leaf_vector":"0"}},{"base_weights":[3.899022E-4,6.361741E-4,2.5177002E-4,8.2736544E-4,1.6479492E-4,3.458659E-5,5.022685E-4],"categories":[],"categories_nodes":[],"categories_segments":[],"categories_sizes":[],"default_left":[true,true,true,false,false,false,false],"id":45,"left_children":[1,3,5,-1,-1,-1,-1],"loss_changes":[1.1325174E-6,1.0352614E-6,1.3971351E-6,6.371074E-7,0E0,2.8175612E-7,9.351336E-7],"parents":[2147483647,0,0,1,1,2,2],"right_children":[2,4,6,-1,-1,-1,-1],"split_conditions":[3.5E3,1.75E2,6.5E3,2.4820963E-4,4.943848E-5,1.0375977E-5,1.5068056E-4],"split_indices":[0,1,0,0,0,0,0],"split_type":[0,0,0,0,0,0,0],"sum_hessian":[3.7E1,1.2E1,2.5E1,8E0,4E0,1.4E1,1.1E1],"tree_param":{"num_deleted":"0","num_feature":"4","num_nodes":"7","size_leaf_vector":"0"}},{"base_weights":[2.8790926E-4,1.6348702E-5,4.284668E-4,5.8555603E-4,1.3427735E-4,1.8988716E-4,9.57489E-4],"categories":[],"categories_nodes":[],"categories_segments":[],"categories_sizes":[],"default_left":[true,false,true,true,false,false,false],"id":46,"left_children":[1,-1,3,5,-1,-1,-1],"loss_changes":[1.4434509E-6,2.428956E-7,1.076723E-6,2.172782E-6,0E0,5.0265527E-8,0E0],"parents":[2147483647,0,0,2,2,3,3],"right_children":[2,-1,4,6,-1,-1,-1],"split_conditions":[1.25E2,4.9046107E-6,1.2E3,6E2,4.0283205E-5,5.696615E-5,2.8724672E-4],"split_indices":[1,0,2,2,0,0,0],"split_type":[0,0,0,0,0,0,0],"sum_hessian":[3.7E1,1.3E1,2.4E1,1.5E1,9E0,8E0,7E0],"tree_param":{"num_deleted":"0","num_feature":"4","num_nodes":"7","size_leaf_vector":"0"}},{"base_weights":[2.1723697E-4],"categories":[],"categories_nodes":[],"categories_segments":[],"categories_sizes":[],"default_left":[false],"id":47,"left_children":[-1],"loss_changes":[7.8719575E-7],"parents":[2147483647],"right_children":[-1],"split_conditions":[6.5171094E-5],"split_indices":[0],"split_type":[0],"sum_hessian":[3.7E1],"tree_param":{"num_deleted":"0","num_feature":"4","num_nodes":"1","size_leaf_vector":"0"}},{"base_weights":[1.57808E-4],"categories":[],"categories_nodes":[],"categories_segments":[],"categories_sizes":[],"default_left":[false],"id":48,"left_children":[-1],"loss_changes":[7.9845506E-7],"parents":[2147483647],"right_children":[-1],"split_conditions":[4.73424E-5],"split_indices":[0],"split_type":[0],"sum_hessian":[3.7E1],"tree_param":{"num_deleted":"0","num_feature":"4","num_nodes":"1","size_leaf_vector":"0"}},{"base_weights":[9.837904E-5],"categories":[],"categories_nodes":[],"categories_segments":[],"categories_sizes":[],"default_left":[false],"id":49,"left_children":[-1],"loss_changes":[8.02898E-7],"parents":[2147483647],"right_children":[-1],"split_conditions":[2.9513712E-5],"split_indices":[0],"split_type":[0],"sum_hessian":[3.7E1],"tree_param":{"num_deleted":"0","num_feature":"4","num_nodes":"1","size_leaf_vector":"0"}},{"base_weights":[6.866455E-5],"categories":[],"categories_nodes":[],"categories_segments":[],"categories_sizes":[],"default_left":[false],"id":50,"left_children":[-1],"loss_changes":[8.0256325E-7],"parents":[2147483647],"right_children":[-1],"split_conditions":[2.0599366E-5],"split_indices":[0],"split_type":[0],"sum_hessian":[3.7E1],"tree_param":{"num_deleted":"0","num_feature":"4","num_nodes":"1","size_leaf_vector":"0"}},{"base_weights":[3.8950067E-5],"categories":[],"categories_nodes":[],"categories_segments":[],"categories_sizes":[],"default_left":[false],"id":51,"left_children":[-1],"loss_changes":[8.0052445E-7],"parents":[2147483647],"right_children":[-1],"split_conditions":[1.1685021E-5],"split_indices":[0],"split_type":[0],"sum_hessian":[3.7E1],"tree_param":{"num_deleted":"0","num_feature":"4","num_nodes":"1","size_leaf_vector":"0"}},{"base_weights":[3.8950067E-5],"categories":[],"categories_nodes":[],"categories_segments":[],"categories_sizes":[],"default_left":[false],"id":52,"left_children":[-1],"loss_changes":[8.0052445E-7],"parents":[2147483647],"right_children":[-1],"split_conditions":[1.1685021E-5],"split_indices":[0],"split_type":[0],"sum_hessian":[3.7E1],"tree_param":{"num_deleted":"0","num_feature":"4","num_nodes":"1","size_leaf_vector":"0"}},{"base_weights":[3.8950067E-5],"categories":[],"categories_nodes":[],"categories_segments":[],"categories_sizes":[],"default_left":[false],"id":53,"left_children":[-1],"loss_changes":[8.0052445E-7],"parents":[2147483647],"right_children":[-1],"split_conditions":[1.1685021E-5],"split_indices":[0],"split_type":[0],"sum_hessian":[3.7E1],"tree_param":{"num_deleted":"0","num_feature":"4","num_nodes":"1","size_leaf_vector":"0"}},{"base_weights":[3.8950067E-5],"categories":[],"categories_nodes":[],"categories_segments":[],"categories_sizes":[],"default_left":[false],"id":54,"left_children":[-1],"loss_changes":[8.0052445E-7],"parents":[2147483647],"right_children":[-1],"split_conditions":[1.1685021E-5],"split_indices":[0],"split_type":[0],"sum_hessian":[3.7E1],"tree_param":{"num_deleted":"0","num_feature":"4","num_nodes":"1","size_leaf_vector":"0"}},{"base_weights":[3.8950067E-5],"categories":[],"categories_nodes":[],"categories_segments":[],"categories_sizes":[],"default_left":[false],"id":55,"left_children":[-1],"loss_changes":[8.0052445E-7],"parents":[2147483647],"right_children":[-1],"split_conditions":[1.1685021E-5],"split_indices":[0],"split_type":[0],"sum_hessian":[3.7E1],"tree_param":{"num_deleted":"0","num_feature":"4","num_nodes":"1","size_leaf_vector":"0"}},{"base_weights":[3.8950067E-5],"categories":[],"categories_nodes":[],"categories_segments":[],"categories_sizes":[],"default_left":[false],"id":56,"left_children":[-1],"loss_changes":[8.0052445E-7],"parents":[2147483647],"right_children":[-1],"split_conditions":[1.1685021E-5],"split_indices":[0],"split_type":[0],"sum_hessian":[3.7E1],"tree_param":{"num_deleted":"0","num_feature":"4","num_nodes":"1","size_leaf_vector":"0"}},{"base_weights":[3.8950067E-5],"categories":[],"categories_nodes":[],"categories_segments":[],"categories_sizes":[],"default_left":[false],"id":57,"left_children":[-1],"loss_changes":[8.0052445E-7],"parents":[2147483647],"right_children":[-1],"split_conditions":[1.1685021E-5],"split_indices":[0],"split_type":[0],"sum_hessian":[3.7E1],"tree_param":{"num_deleted":"0","num_feature":"4","num_nodes":"1","size_leaf_vector":"0"}},{"base_weights":[3.8950067E-5],"categories":[],"categories_nodes":[],"categories_segments":[],"categories_sizes":[],"default_left":[false],"id":58,"left_children":[-1],"loss_changes":[8.0052445E-7],"parents":[2147483647],"right_children":[-1],"split_conditions":[1.1685021E-5],"split_indices":[0],"split_type":[0],"sum_hessian":[3.7E1],"tree_param":{"num_deleted":"0","num_feature":"4","num_nodes":"1","size_leaf_vector":"0"}},{"base_weights":[3.8950067E-5],"categories":[],"categories_nodes":[],"categories_segments":[],"categories_sizes":[],"default_left":[false],"id":59,"left_children":[-1],"loss_changes":[8.0052445E-7],"parents":[2147483647],"right_children":[-1],"split_conditions":[1.1685021E-5],"split_indices":[0],"split_type":[0],"sum_hessian":[3.7E1],"tree_param":{"num_deleted":"0","num_feature":"4","num_nodes":"1","size_leaf_vector":"0"}},{"base_weights":[3.8950067E-5],"categories":[],"categories_nodes":[],"categories_segments":[],"categories_sizes":[],"default_left":[false],"id":60,"left_children":[-1],"loss_changes":[8.0052445E-7],"parents":[2147483647],"right_children":[-1],"split_conditions":[1.1685021E-5],"split_indices":[0],"split_type":[0],"sum_hessian":[3.7E1],"tree_param":{"num_deleted":"0","num_feature":"4","num_nodes":"1","size_leaf_vector":"0"}},{"base_weights":[3.8950067E-5],"categories":[],"categories_nodes":[],"categories_segments":[],"categories_sizes":[],"default_left":[false],"id":61,"left_children":[-1],"loss_changes":[8.0052445E-7],"parents":[2147483647],"right_children":[-1],"split_conditions":[1.1685021E-5],"split_indices":[0],"split_type":[0],"sum_hessian":[3.7E1],"tree_param":{"num_deleted":"0","num_feature":"4","num_nodes":"1","size_leaf_vector":"0"}},{"base_weights":[3.8950067E-5],"categories":[],"categories_nodes":[],"categories_segments":[],"categories_sizes":[],"default_left":[false],"id":62,"left_children":[-1],"loss_changes":[8.0052445E-7],"parents":[2147483647],"right_children":[-1],"split_conditions":[1.1685021E-5],"split_indices":[0],"split_type":[0],"sum_hessian":[3.7E1],"tree_param":{"num_deleted":"0","num_feature":"4","num_nodes":"1","size_leaf_vector":"0"}},{"base_weights":[3.8950067E-5],"categories":[],"categories_nodes":[],"categories_segments":[],"categories_sizes":[],"default_left":[false],"id":63,"left_children":[-1],"loss_changes":[8.0052445E-7],"parents":[2147483647],"right_children":[-1],"split_conditions":[1.1685021E-5],"split_indices":[0],"split_type":[0],"sum_hessian":[3.7E1],"tree_param":{"num_deleted":"0","num_feature":"4","num_nodes":"1","size_leaf_vector":"0"}},{"base_weights":[3.8950067E-5],"categories":[],"categories_nodes":[],"categories_segments":[],"categories_sizes":[],"default_left":[false],"id":64,"left_children":[-1],"loss_changes":[8.0052445E-7],"parents":[2147483647],"right_children":[-1],"split_conditions":[1.1685021E-5],"split_indices":[0],"split_type":[0],"sum_hessian":[3.7E1],"tree_param":{"num_deleted":"0","num_feature":"4","num_nodes":"1","size_leaf_vector":"0"}},{"base_weights":[3.8950067E-5],"categories":[],"categories_nodes":[],"categories_segments":[],"categories_sizes":[],"default_left":[false],"id":65,"left_children":[-1],"loss_changes":[8.0052445E-7],"parents":[2147483647],"right_children":[-1],"split_conditions":[1.1685021E-5],"split_indices":[0],"split_type":[0],"sum_hessian":[3.7E1],"tree_param":{"num_deleted":"0","num_feature":"4","num_nodes":"1","size_leaf_vector":"0"}},{"base_weights":[3.8950067E-5],"categories":[],"categories_nodes":[],"categories_segments":[],"categories_sizes":[],"default_left":[false],"id":66,"left_children":[-1],"loss_changes":[8.0052445E-7],"parents":[2147483647],"right_children":[-1],"split_conditions":[1.1685021E-5],"split_indices":[0],"split_type":[0],"sum_hessian":[3.7E1],"tree_param":{"num_deleted":"0","num_feature":"4","num_nodes":"1","size_leaf_vector":"0"}},{"base_weights":[3.8950067E-5],"categories":[],"categories_nodes":[],"categories_segments":[],"categories_sizes":[],"default_left":[false],"id":67,"left_children":[-1],"loss_changes":[8.0052445E-7],"parents":[2147483647],"right_children":[-1],"split_conditions":[1.1685021E-5],"split_indices":[0],"split_type":[0],"sum_hessian":[3.7E1],"tree_param":{"num_deleted":"0","num_feature":"4","num_nodes":"1","size_leaf_vector":"0"}},{"base_weights":[3.8950067E-5],"categories":[],"categories_nodes":[],"categories_segments":[],"categories_sizes":[],"default_left":[false],"id":68,"left_children":[-1],"loss_changes":[8.0052445E-7],"parents":[2147483647],"right_children":[-1],"split_conditions":[1.1685021E-5],"split_indices":[0],"split_type":[0],"sum_hessian":[3.7E1],"tree_param":{"num_deleted":"0","num_feature":"4","num_nodes":"1","size_leaf_vector":"0"}},{"base_weights":[3.8950067E-5],"categories":[],"categories_nodes":[],"categories_segments":[],"categories_sizes":[],"default_left":[false],"id":69,"left_children":[-1],"loss_changes":[8.0052445E-7],"parents":[2147483647],"right_children":[-1],"split_conditions":[1.1685021E-5],"split_indices":[0],"split_type":[0],"sum_hessian":[3.7E1],"tree_param":{"num_deleted":"0","num_feature":"4","num_nodes":"1","size_leaf_vector":"0"}},{"base_weights":[3.8950067E-5],"categories":[],"categories_nodes":[],"categories_segments":[],"categories_sizes":[],"default_left":[false],"id":70,"left_children":[-1],"loss_changes":[8.0052445E-7],"parents":[2147483647],"right_children":[-1],"split_conditions":[1.1685021E-5],"split_indices":[0],"split_type":[0],"sum_hessian":[3.7E1],"tree_param":{"num_deleted":"0","num_feature":"4","num_nodes":"1","size_leaf_vector":"0"}},{"base_weights":[3.8950067E-5],"categories":[],"categories_nodes":[],"categories_segments":[],"categories_sizes":[],"default_left":[false],"id":71,"left_children":[-1],"loss_changes":[8.0052445E-7],"parents":[2147483647],"right_children":[-1],"split_conditions":[1.1685021E-5],"split_indices":[0],"split_type":[0],"sum_hessian":[3.7E1],"tree_param":{"num_deleted":"0","num_feature":"4","num_nodes":"1","size_leaf_vector":"0"}},{"base_weights":[3.8950067E-5],"categories":[],"categories_nodes":[],"categories_segments":[],"categories_sizes":[],"default_left":[false],"id":72,"left_children":[-1],"loss_changes":[8.0052445E-7],"parents":[2147483647],"right_children":[-1],"split_conditions":[1.1685021E-5],"split_indices":[0],"split_type":[0],"sum_hessian":[3.7E1],"tree_param":{"num_deleted":"0","num_feature":"4","num_nodes":"1","size_leaf_vector":"0"}},{"base_weights":[3.8950067E-5],"categories":[],"categories_nodes":[],"categories_segments":[],"categories_sizes":[],"default_left":[false],"id":73,"left_children":[-1],"loss_changes":[8.0052445E-7],"parents":[2147483647],"right_children":[-1],"split_conditions":[1.1685021E-5],"split_indices":[0],"split_type":[0],"sum_hessian":[3.7E1],"tree_param":{"num_deleted":"0","num_feature":"4","num_nodes":"1","size_leaf_vector":"0"}},{"base_weights":[3.8950067E-5],"categories":[],"categories_nodes":[],"categories_segments":[],"categories_sizes":[],"default_left":[false],"id":74,"left_children":[-1],"loss_changes":[8.0052445E-7],"parents":[2147483647],"right_children":[-1],"split_conditions":[1.1685021E-5],"split_indices":[0],"split_type":[0],"sum_hessian":[3.7E1],"tree_param":{"num_deleted":"0","num_feature":"4","num_nodes":"1","size_leaf_vector":"0"}},{"base_weights":[3.8950067E-5],"categories":[],"categories_nodes":[],"categories_segments":[],"categories_sizes":[],"default_left":[false],"id":75,"left_children":[-1],"loss_changes":[8.0052445E-7],"parents":[2147483647],"right_children":[-1],"split_conditions":[1.1685021E-5],"split_indices":[0],"split_type":[0],"sum_hessian":[3.7E1],"tree_param":{"num_deleted":"0","num_feature":"4","num_nodes":"1","size_leaf_vector":"0"}},{"base_weights":[3.8950067E-5],"categories":[],"categories_nodes":[],"categories_segments":[],"categories_sizes":[],"default_left":[false],"id":76,"left_children":[-1],"loss_changes":[8.0052445E-7],"parents":[2147483647],"right_children":[-1],"split_conditions":[1.1685021E-5],"split_indices":[0],"split_type":[0],"sum_hessian":[3.7E1],"tree_param":{"num_deleted":"0","num_feature":"4","num_nodes":"1","size_leaf_vector":"0"}},{"base_weights":[3.8950067E-5],"categories":[],"categories_nodes":[],"categories_segments":[],"categories_sizes":[],"default_left":[false],"id":77,"left_children":[-1],"loss_changes":[8.0052445E-7],"parents":[2147483647],"right_children":[-1],"split_conditions":[1.1685021E-5],"split_indices":[0],"split_type":[0],"sum_hessian":[3.7E1],"tree_param":{"num_deleted":"0","num_feature":"4","num_nodes":"1","size_leaf_vector":"0"}},{"base_weights":[3.8950067E-5],"categories":[],"categories_nodes":[],"categories_segments":[],"categories_sizes":[],"default_left":[false],"id":78,"left_children":[-1],"loss_changes":[8.0052445E-7],"parents":[2147483647],"right_children":[-1],"split_conditions":[1.1685021E-5],"split_indices":[0],"split_type":[0],"sum_hessian":[3.7E1],"tree_param":{"num_deleted":"0","num_feature":"4","num_nodes":"1","size_leaf_vector":"0"}},{"base_weights":[3.8950067E-5],"categories":[],"categories_nodes":[],"categories_segments":[],"categories_sizes":[],"default_left":[false],"id":79,"left_children":[-1],"loss_changes":[8.0052445E-7],"parents":[2147483647],"right_children":[-1],"split_conditions":[1.1685021E-5],"split_indices":[0],"split_type":[0],"sum_hessian":[3.7E1],"tree_param":{"num_deleted":"0","num_feature":"4","num_nodes":"1","size_leaf_vector":"0"}},{"base_weights":[3.8950067E-5],"categories":[],"categories_nodes":[],"categories_segments":[],"categories_sizes":[],"default_left":[false],"id":80,"left_children":[-1],"loss_changes":[8.0052445E-7],"parents":[2147483647],"right_children":[-1],"split_conditions":[1.1685021E-5],"split_indices":[0],"split_type":[0],"sum_hessian":[3.7E1],"tree_param":{"num_deleted":"0","num_feature":"4","num_nodes":"1","size_leaf_vector":"0"}},{"base_weights":[3.8950067E-5],"categories":[],"categories_nodes":[],"categories_segments":[],"categories_sizes":[],"default_left":[false],"id":81,"left_children":[-1],"loss_changes":[8.0052445E-7],"parents":[2147483647],"right_children":[-1],"split_conditions":[1.1685021E-5],"split_indices":[0],"split_type":[0],"sum_hessian":[3.7E1],"tree_param":{"num_deleted":"0","num_feature":"4","num_nodes":"1","size_leaf_vector":"0"}},{"base_weights":[3.8950067E-5],"categories":[],"categories_nodes":[],"categories_segments":[],"categories_sizes":[],"default_left":[false],"id":82,"left_children":[-1],"loss_changes":[8.0052445E-7],"parents":[2147483647],"right_children":[-1],"split_conditions":[1.1685021E-5],"split_indices":[0],"split_type":[0],"sum_hessian":[3.7E1],"tree_param":{"num_deleted":"0","num_feature":"4","num_nodes":"1","size_leaf_vector":"0"}},{"base_weights":[3.8950067E-5],"categories":[],"categories_nodes":[],"categories_segments":[],"categories_sizes":[],"default_left":[false],"id":83,"left_children":[-1],"loss_changes":[8.0052445E-7],"parents":[2147483647],"right_children":[-1],"split_conditions":[1.1685021E-5],"split_indices":[0],"split_type":[0],"sum_hessian":[3.7E1],"tree_param":{"num_deleted":"0","num_feature":"4","num_nodes":"1","size_leaf_vector":"0"}},{"base_weights":[3.8950067E-5],"categories":[],"categories_nodes":[],"categories_segments":[],"categories_sizes":[],"default_left":[false],"id":84,"left_children":[-1],"loss_changes":[8.0052445E-7],"parents":[2147483647],"right_children":[-1],"split_conditions":[1.1685021E-5],"split_indices":[0],"split_type":[0],"sum_hessian":[3.7E1],"tree_param":{"num_deleted":"0","num_feature":"4","num_nodes":"1","size_leaf_vector":"0"}},{"base_weights":[3.8950067E-5],"categories":[],"categories_nodes":[],"categories_segments":[],"categories_sizes":[],"default_left":[false],"id":85,"left_children":[-1],"loss_changes":[8.0052445E-7],"parents":[2147483647],"right_children":[-1],"split_conditions":[1.1685021E-5],"split_indices":[0],"split_type":[0],"sum_hessian":[3.7E1],"tree_param":{"num_deleted":"0","num_feature":"4","num_nodes":"1","size_leaf_vector":"0"}},{"base_weights":[3.8950067E-5],"categories":[],"categories_nodes":[],"categories_segments":[],"categories_sizes":[],"default_left":[false],"id":86,"left_children":[-1],"loss_changes":[8.0052445E-7],"parents":[2147483647],"right_children":[-1],"split_conditions":[1.1685021E-5],"split_indices":[0],"split_type":[0],"sum_hessian":[3.7E1],"tree_param":{"num_deleted":"0","num_feature":"4","num_nodes":"1","size_leaf_vector":"0"}},{"base_weights":[3.8950067E-5],"categories":[],"categories_nodes":[],"categories_segments":[],"categories_sizes":[],"default_left":[false],"id":87,"left_children":[-1],"loss_changes":[8.0052445E-7],"parents":[2147483647],"right_children":[-1],"split_conditions":[1.1685021E-5],"split_indices":[0],"split_type":[0],"sum_hessian":[3.7E1],"tree_param":{"num_deleted":"0","num_feature":"4","num_nodes":"1","size_leaf_vector":"0"}},{"base_weights":[3.8950067E-5],"categories":[],"categories_nodes":[],"categories_segments":[],"categories_sizes":[],"default_left":[false],"id":88,"left_children":[-1],"loss_changes":[8.0052445E-7],"parents":[2147483647],"right_children":[-1],"split_conditions":[1.1685021E-5],"split_indices":[0],"split_type":[0],"sum_hessian":[3.7E1],"tree_param":{"num_deleted":"0","num_feature":"4","num_nodes":"1","size_leaf_vector":"0"}},{"base_weights":[3.8950067E-5],"categories":[],"categories_nodes":[],"categories_segments":[],"categories_sizes":[],"default_left":[false],"id":89,"left_children":[-1],"loss_changes":[8.0052445E-7],"parents":[2147483647],"right_children":[-1],"split_conditions":[1.1685021E-5],"split_indices":[0],"split_type":[0],"sum_hessian":[3.7E1],"tree_param":{"num_deleted":"0","num_feature":"4","num_nodes":"1","size_leaf_vector":"0"}},{"base_weights":[3.8950067E-5],"categories":[],"categories_nodes":[],"categories_segments":[],"categories_sizes":[],"default_left":[false],"id":90,"left_children":[-1],"loss_changes":[8.0052445E-7],"parents":[2147483647],"right_children":[-1],"split_conditions":[1.1685021E-5],"split_indices":[0],"split_type":[0],"sum_hessian":[3.7E1],"tree_param":{"num_deleted":"0","num_feature":"4","num_nodes":"1","size_leaf_vector":"0"}},{"base_weights":[3.8950067E-5],"categories":[],"categories_nodes":[],"categories_segments":[],"categories_sizes":[],"default_left":[false],"id":91,"left_children":[-1],"loss_changes":[8.0052445E-7],"parents":[2147483647],"right_children":[-1],"split_conditions":[1.1685021E-5],"split_indices":[0],"split_type":[0],"sum_hessian":[3.7E1],"tree_param":{"num_deleted":"0","num_feature":"4","num_nodes":"1","size_leaf_vector":"0"}},{"base_weights":[3.8950067E-5],"categories":[],"categories_nodes":[],"categories_segments":[],"categories_sizes":[],"default_left":[false],"id":92,"left_children":[-1],"loss_changes":[8.0052445E-7],"parents":[2147483647],"right_children":[-1],"split_conditions":[1.1685021E-5],"split_indices":[0],"split_type":[0],"sum_hessian":[3.7E1],"tree_param":{"num_deleted":"0","num_feature":"4","num_nodes":"1","size_leaf_vector":"0"}},{"base_weights":[3.8950067E-5],"categories":[],"categories_nodes":[],"categories_segments":[],"categories_sizes":[],"default_left":[false],"id":93,"left_children":[-1],"loss_changes":[8.0052445E-7],"parents":[2147483647],"right_children":[-1],"split_conditions":[1.1685021E-5],"split_indices":[0],"split_type":[0],"sum_hessian":[3.7E1],"tree_param":{"num_deleted":"0","num_feature":"4","num_nodes":"1","size_leaf_vector":"0"}},{"base_weights":[3.8950067E-5],"categories":[],"categories_nodes":[],"categories_segments":[],"categories_sizes":[],"default_left":[false],"id":94,"left_children":[-1],"loss_changes":[8.0052445E-7],"parents":[2147483647],"right_children":[-1],"split_conditions":[1.1685021E-5],"split_indices":[0],"split_type":[0],"sum_hessian":[3.7E1],"tree_param":{"num_deleted":"0","num_feature":"4","num_nodes":"1","size_leaf_vector":"0"}},{"base_weights":[3.8950067E-5],"categories":[],"categories_nodes":[],"categories_segments":[],"categories_sizes":[],"default_left":[false],"id":95,"left_children":[-1],"loss_changes":[8.0052445E-7],"parents":[2147483647],"right_children":[-1],"split_conditions":[1.1685021E-5],"split_indices":[0],"split_type":[0],"sum_hessian":[3.7E1],"tree_param":{"num_deleted":"0","num_feature":"4","num_nodes":"1","size_leaf_vector":"0"}},{"base_weights":[3.8950067E-5],"categories":[],"categories_nodes":[],"categories_segments":[],"categories_sizes":[],"default_left":[false],"id":96,"left_children":[-1],"loss_changes":[8.0052445E-7],"parents":[2147483647],"right_children":[-1],"split_conditions":[1.1685021E-5],"split_indices":[0],"split_type":[0],"sum_hessian":[3.7E1],"tree_param":{"num_deleted":"0","num_feature":"4","num_nodes":"1","size_leaf_vector":"0"}},{"base_weights":[3.8950067E-5],"categories":[],"categories_nodes":[],"categories_segments":[],"categories_sizes":[],"default_left":[false],"id":97,"left_children":[-1],"loss_changes":[8.0052445E-7],"parents":[2147483647],"right_children":[-1],"split_conditions":[1.1685021E-5],"split_indices":[0],"split_type":[0],"sum_hessian":[3.7E1],"tree_param":{"num_deleted":"0","num_feature":"4","num_nodes":"1","size_leaf_vector":"0"}},{"base_weights":[3.8950067E-5],"categories":[],"categories_nodes":[],"categories_segments":[],"categories_sizes":[],"default_left":[false],"id":98,"left_children":[-1],"loss_changes":[8.0052445E-7],"parents":[2147483647],"right_children":[-1],"split_conditions":[1.1685021E-5],"split_indices":[0],"split_type":[0],"sum_hessian":[3.7E1],"tree_param":{"num_deleted":"0","num_feature":"4","num_nodes":"1","size_leaf_vector":"0"}},{"base_weights":[3.8950067E-5],"categories":[],"categories_nodes":[],"categories_segments":[],"categories_sizes":[],"default_left":[false],"id":99,"left_children":[-1],"loss_changes":[8.0052445E-7],"parents":[2147483647],"right_children":[-1],"split_conditions":[1.1685021E-5],"split_indices":[0],"split_type":[0],"sum_hessian":[3.7E1],"tree_param":{"num_deleted":"0","num_feature":"4","num_nodes":"1","size_leaf_vector":"0"}}]},"name":"gbtree"},"learner_model_param":{"base_score":"5E-1","num_class":"0","num_feature":"4"},"objective":{"name":"reg:squarederror","reg_loss_param":{"scale_pos_weight":"1"}}},"version":[1,5,1]}